uw_django_saml2-1.8.4.dist-info/licenses/LICENSE
uw_saml/VERSION
uw_saml/__init__.py
uw_saml/attributes.py
uw_saml/auth.py
uw_saml/decorators.py
uw_saml/urls.py
uw_saml/utils.py
uw_saml/views.py
uw_saml/templates/uw_saml/access_denied.html
uw_saml/templates/uw_saml/sso_error.html
uw_saml/templates/uw_saml/mock/base.html
uw_saml/templates/uw_saml/mock/login.html
uw_saml/templates/uw_saml/mock/logout.html
uw_saml/tests/__init__.py
uw_saml/tests/test_auth.py
uw_saml/tests/test_decorators.py
uw_saml/tests/test_utils.py
uw_saml/tests/test_views.py
uw_django_saml2-1.8.4.dist-info/METADATA
uw_django_saml2-1.8.4.dist-info/WHEEL
uw_django_saml2-1.8.4.dist-info/top_level.txt
uw_django_saml2-1.8.4.dist-info/RECORD
