Metadata-Version: 2.4
Name: uw-django-saml2
Version: 1.8.4
Summary: Django wrapper for python3-saml
Home-page: https://github.com/uw-it-aca/uw-django-saml2
Author: UW-IT T&LS
Author-email: aca-it@uw.edu
License: Apache License, Version 2.0
Classifier: Intended Audience :: Developers
Classifier: License :: OSI Approved :: Apache Software License
Classifier: Operating System :: OS Independent
Classifier: Programming Language :: Python
Classifier: Framework :: Django
License-File: LICENSE
Requires-Dist: django<6,>=3.2
Requires-Dist: python3-saml~=1.16
Requires-Dist: lxml==5.3.1
Requires-Dist: xmlsec==1.3.14
Requires-Dist: mock
Dynamic: author
Dynamic: author-email
Dynamic: classifier
Dynamic: description
Dynamic: home-page
Dynamic: license
Dynamic: license-file
Dynamic: requires-dist
Dynamic: summary
